LICENSE
README.md
setup.py
randomText/__init__.py
randomText/__version__.py
randomText/client.py
randomText/src/base_dad.py
randomText/src/base_evil.py
randomText/src/base_faker.py
randomText/src/base_geek.py
randomText/src/base_meta.py
randomText/src/base_random.py
randomText/src/base_randommer.py
randomText/src/base_shibe.py
randomText/src/base_testimonial.py
randomText/src/dad_endpoints.py
randomText/src/endpoints.py
randomText/src/evil_endpoints.py
randomText/src/faker_endpoints.py
randomText/src/geek_endpoints.py
randomText/src/meta_endpoints.py
randomText/src/new_endpoints.py
randomText/src/shibe_endpoints.py
randomText/src/testimonial_endpoints.py
random_text.egg-info/PKG-INFO
random_text.egg-info/SOURCES.txt
random_text.egg-info/dependency_links.txt
random_text.egg-info/not-zip-safe
random_text.egg-info/requires.txt
random_text.egg-info/top_level.txt