Metadata-Version: 2.1
Name: random-text
Version: 1.8.0
Summary: A Python client library Random Data Api
Home-page: https://github.com/uricod/random-text
Author: josh nussbaum
Author-email: joshnuss2@gmail.com
License: BSD
Classifier: Programming Language :: Python :: 3
Classifier: Programming Language :: Python :: 3.6
Classifier: Programming Language :: Python :: 3.7
Classifier: Programming Language :: Python :: 3.8
Classifier: Operating System :: OS Independent
Requires-Python: >=3.6
License-File: LICENSE
